{"map_file_path": "grid_maps/Wiconisco/occ_grid_small.txt", "start_pos": [8, 65], "goal_pos": [76, 33], "robot_rows": [8, 8, 8, 9, 11, 14, 17, 20, 23, 26, 29, 31, 33, 34, 34, 34, 34, 34, 34, 34, 34, 34, 34, 34, 34, 34, 34, 34, 34, 35, 37, 40, 42, 44, 47, 50, 53, 56, 59, 62, 65, 68, 71, 73, 75, 76, 76, 76, 76, 76, 76, 76, 76], "robot_cols": [65, 65, 65, 65, 65, 65, 65, 65, 65, 65, 65, 65, 65, 65, 65, 65, 64, 62, 59, 56, 53, 50, 47, 44, 42, 40, 39, 39, 39, 39, 39, 39, 39, 39, 39, 39, 39, 39, 39, 39, 39, 39, 39, 39, 39, 39, 39, 39, 38, 36, 34, 33, 33], "robot_speeds": [0, 0, 0, 1, 2, 3, 3, 3, 3, 3, 3, 2, 2, 1, 0, 0, 1, 2, 3, 3, 3, 3, 3, 3, 2, 2, 1, 0, 0, 1, 2, 3, 2, 2, 3, 3, 3, 3, 3, 3, 3, 3, 3, 2, 2, 1, 0, 0, 1, 2, 2, 1, 0], "robot_directions": [0, 0, 3, 3, 3, 3, 3, 3, 3, 3, 3, 3, 3, 3, 3, 0, 0, 0, 0, 0, 0, 0, 0, 0, 0, 0, 0, 0, 3, 3, 3, 3, 3, 3, 3, 3, 3, 3, 3, 3, 3, 3, 3, 3, 3, 3, 3, 0, 0, 0, 0, 0, 0], "action_accs": [-1, 0, 1, 1, 1, 0, 0, 1, 0, 0, -1, 0, -1, 0, 0, 1, 1, 1, 0, 0, 0, 1, 0, -1, 0, -1, -1, 0, 1, 1, 1, -1, 0, 1, 0, 0, 0, 0, 0, 0, 0, 0, -1, 0, -1, -1, 0, 1, 1, 0, -1, -1], "action_rots": [0, -1, 0, 0, 0, 0, 0, 0, 0, 0, 0, 0, 0, 0, 1, 0, 0, 0, 0, 0, 0, 0, 0, 0, 0, 0, 0, -1, 0, 0, 0, 0, 0, 0, 0, 0, 0, 0, 0, 0, 0, 0, 0, 0, 0, 0, 1, 0, 0, 0, 0, 0], "steps": 52, "is_goal": true}