{"map_file_path": "grid_maps/Wiconisco/occ_grid_small.txt", "start_pos": [1, 53], "goal_pos": [33, 86], "robot_rows": [1, 1, 1, 2, 4, 6, 9, 12, 15, 18, 21, 24, 27, 30, 32, 33, 33, 33, 33, 33, 33, 33, 33, 33, 33, 33, 33, 33, 33, 33, 33, 33], "robot_cols": [53, 53, 53, 53, 53, 53, 53, 53, 53, 53, 53, 53, 53, 53, 53, 53, 53, 53, 54, 56, 59, 62, 65, 68, 71, 74, 77, 80, 83, 85, 86, 86], "robot_speeds": [0, 0, 0, 1, 2, 2, 3, 3, 3, 3, 3, 3, 3, 3, 2, 1, 0, 0, 1, 2, 3, 3, 3, 3, 3, 3, 3, 3, 3, 2, 1, 0], "robot_directions": [0, 0, 3, 3, 3, 3, 3, 3, 3, 3, 3, 3, 3, 3, 3, 3, 3, 2, 2, 2, 2, 2, 2, 2, 2, 2, 2, 2, 2, 2, 2, 2], "action_accs": [-1, 0, 1, 1, 0, 1, 0, 0, 0, 0, 0, 1, 0, -1, -1, -1, 0, 1, 1, 1, 0, 0, 0, 0, 0, 0, 0, 0, -1, -1, -1], "action_rots": [0, -1, 0, 0, 0, 0, 0, 0, 0, 0, 0, 0, 0, 0, 0, 0, -1, 0, 0, 0, 0, 0, 0, 0, 0, 0, 0, 0, 0, 0, 0], "steps": 31, "is_goal": true}