{"map_file_path": "grid_maps/Wiconisco/occ_grid_small.txt", "start_pos": [83, 38], "goal_pos": [24, 10], "robot_rows": [83, 83, 83, 83, 83, 83, 83, 83, 83, 83, 83, 83, 83, 83, 82, 80, 77, 75, 72, 69, 66, 63, 61, 58, 55, 52, 49, 46, 43, 40, 37, 35, 33, 31, 28, 26, 25, 24, 24, 24, 24, 24, 24, 24], "robot_cols": [38, 38, 37, 35, 32, 29, 26, 23, 20, 17, 15, 14, 14, 14, 14, 14, 14, 14, 14, 14, 14, 14, 14, 14, 14, 14, 14, 14, 14, 14, 14, 14, 14, 14, 14, 14, 14, 14, 14, 14, 13, 11, 10, 10], "robot_speeds": [0, 0, 1, 2, 3, 3, 3, 3, 3, 3, 2, 1, 0, 0, 1, 2, 3, 2, 3, 3, 3, 3, 2, 3, 3, 3, 3, 3, 3, 3, 3, 2, 2, 2, 3, 2, 1, 1, 0, 0, 1, 2, 1, 0], "robot_directions": [0, 0, 0, 0, 0, 0, 0, 0, 0, 0, 0, 0, 0, 1, 1, 1, 1, 1, 1, 1, 1, 1, 1, 1, 1, 1, 1, 1, 1, 1, 1, 1, 1, 1, 1, 1, 1, 1, 1, 0, 0, 0, 0, 0], "action_accs": [-1, 1, 1, 1, 0, 0, 0, 0, 0, -1, -1, -1, 0, 1, 1, 1, -1, 1, 0, 0, 0, -1, 1, 0, 0, 0, 0, 0, 0, 0, -1, 0, 0, 1, -1, -1, 0, -1, 0, 1, 1, -1, -1], "action_rots": [0, 0, 0, 0, 0, 0, 0, 0, 0, 0, 0, 0, 1, 0, 0, 0, 0, 0, 0, 0, 0, 0, 0, 0, 0, 0, 0, 0, 0, 0, 0, 0, 0, 0, 0, 0, 0, 0, -1, 0, 0, 0, 0], "steps": 43, "is_goal": true}