{"map_file_path": "grid_maps/Wiconisco/occ_grid_small.txt", "start_pos": [82, 14], "goal_pos": [43, 44], "robot_rows": [82, 82, 82, 81, 79, 77, 74, 71, 68, 65, 62, 59, 56, 53, 50, 47, 45, 44, 43, 43, 43, 43, 43, 43, 43, 43, 43, 43, 43, 43, 43, 43, 43, 43, 43], "robot_cols": [14, 14, 14, 14, 14, 14, 14, 14, 14, 14, 14, 14, 14, 14, 14, 14, 14, 14, 14, 14, 14, 14, 15, 17, 20, 23, 26, 29, 32, 35, 38, 41, 43, 44, 44], "robot_speeds": [0, 0, 0, 1, 2, 2, 3, 3, 3, 3, 3, 3, 3, 3, 3, 3, 2, 1, 1, 0, 0, 0, 1, 2, 3, 3, 3, 3, 3, 3, 3, 3, 2, 1, 0], "robot_directions": [0, 0, 1, 1, 1, 1, 1, 1, 1, 1, 1, 1, 1, 1, 1, 1, 1, 1, 1, 1, 2, 2, 2, 2, 2, 2, 2, 2, 2, 2, 2, 2, 2, 2, 2], "action_accs": [-1, 0, 1, 1, 0, 1, 0, 0, 0, 0, 0, 0, 0, 0, 0, -1, -1, 0, -1, 0, 0, 1, 1, 1, 0, 0, 0, 0, 0, 0, 0, -1, -1, -1], "action_rots": [0, 1, 0, 0, 0, 0, 0, 0, 0, 0, 0, 0, 0, 0, 0, 0, 0, 0, 0, 1, 0, 0, 0, 0, 0, 0, 0, 0, 0, 0, 0, 0, 0, 0], "steps": 34, "is_goal": true}