{"map_file_path": "grid_maps/Wiconisco/occ_grid_small.txt", "start_pos": [53, 2], "goal_pos": [21, 84], "robot_rows": [53, 53, 53, 52, 50, 48, 45, 43, 42, 41, 41, 41, 41, 41, 41, 41, 40, 38, 35, 32, 29, 26, 24, 22, 21, 21, 21, 21, 21, 21, 21, 21, 21, 21, 21, 21, 21, 21, 21, 21, 21, 21, 21, 21, 21, 21, 21, 21, 21, 21, 21, 21, 21, 21, 21, 21, 21], "robot_cols": [2, 2, 2, 2, 2, 2, 2, 2, 2, 2, 2, 2, 3, 4, 4, 4, 4, 4, 4, 4, 4, 4, 4, 4, 4, 4, 4, 5, 7, 10, 13, 16, 19, 22, 25, 28, 31, 34, 37, 40, 43, 46, 49, 52, 55, 58, 61, 64, 66, 69, 72, 75, 78, 81, 83, 84, 84], "robot_speeds": [0, 0, 0, 1, 2, 2, 3, 2, 1, 1, 0, 0, 1, 1, 0, 0, 1, 2, 3, 3, 3, 3, 2, 2, 1, 0, 0, 1, 2, 3, 3, 3, 3, 3, 3, 3, 3, 3, 3, 3, 3, 3, 3, 3, 3, 3, 3, 3, 2, 3, 3, 3, 3, 3, 2, 1, 0], "robot_directions": [0, 0, 1, 1, 1, 1, 1, 1, 1, 1, 1, 2, 2, 2, 2, 1, 1, 1, 1, 1, 1, 1, 1, 1, 1, 1, 2, 2, 2, 2, 2, 2, 2, 2, 2, 2, 2, 2, 2, 2, 2, 2, 2, 2, 2, 2, 2, 2, 2, 2, 2, 2, 2, 2, 2, 2, 2], "action_accs": [-1, 0, 1, 1, 0, 1, -1, -1, 0, -1, 0, 1, 0, -1, 0, 1, 1, 1, 0, 0, 0, -1, 0, -1, -1, 0, 1, 1, 1, 0, 0, 0, 0, 0, 0, 0, 0, 1, 0, 0, 0, 0, 0, 0, 0, 0, 0, -1, 1, 0, 0, 0, 0, -1, -1, -1], "action_rots": [0, 1, 0, 0, 0, 0, 0, 0, 0, 0, 1, 0, 0, 0, -1, 0, 0, 0, 0, 0, 0, 0, 0, 0, 0, 1, 0, 0, 0, 0, 0, 0, 0, 0, 0, 0, 0, 0, 0, 0, 0, 0, 0, 0, 0, 0, 0, 0, 0, 0, 0, 0, 0, 0, 0, 0], "steps": 56, "is_goal": true}