{"map_file_path": "grid_maps/Wiconisco/occ_grid_small.txt", "start_pos": [34, 22], "goal_pos": [46, 77], "robot_rows": [34, 34, 34, 34, 34, 34, 34, 34, 34, 34, 34, 34, 34, 34, 34, 34, 34, 34, 34, 34, 34, 34, 34, 35, 37, 39, 42, 45, 48, 50, 52, 53, 53, 53, 53, 53, 53, 53, 53, 53, 53, 53, 53, 53, 53, 53, 53, 53, 53, 53, 53, 52, 50, 49, 48, 48, 47, 46, 46, 46, 46, 46, 46], "robot_cols": [22, 22, 22, 22, 23, 24, 26, 28, 30, 33, 36, 39, 42, 44, 46, 47, 48, 48, 48, 48, 47, 47, 47, 47, 47, 47, 47, 47, 47, 47, 47, 47, 47, 47, 47, 48, 50, 53, 55, 58, 61, 64, 67, 70, 73, 75, 77, 78, 78, 78, 78, 78, 78, 78, 78, 78, 78, 78, 78, 78, 78, 77, 77], "robot_speeds": [0, 0, 0, 0, 1, 1, 2, 2, 2, 3, 3, 3, 3, 2, 2, 1, 1, 0, 0, 0, 1, 0, 0, 1, 2, 2, 3, 3, 3, 2, 2, 1, 0, 0, 0, 1, 2, 3, 2, 3, 3, 3, 3, 3, 3, 2, 2, 1, 0, 0, 0, 1, 2, 1, 1, 0, 1, 1, 0, 0, 0, 1, 0], "robot_directions": [0, 0, 3, 2, 2, 2, 2, 2, 2, 2, 2, 2, 2, 2, 2, 2, 2, 2, 3, 0, 0, 0, 3, 3, 3, 3, 3, 3, 3, 3, 3, 3, 3, 2, 2, 2, 2, 2, 2, 2, 2, 2, 2, 2, 2, 2, 2, 2, 2, 1, 1, 1, 1, 1, 1, 1, 1, 1, 1, 0, 0, 0, 0], "action_accs": [-1, 0, 0, 1, 0, 1, 0, 0, 1, 0, 0, 0, -1, 0, -1, 0, -1, 0, 0, 1, -1, 0, 1, 1, 0, 1, 0, 0, -1, 0, -1, -1, 0, 0, 1, 1, 1, -1, 1, 0, 0, 1, 0, 0, -1, 0, -1, -1, 0, 0, 1, 1, -1, 0, -1, 1, 0, -1, 0, 0, 1, -1], "action_rots": [0, -1, -1, 0, 0, 0, 0, 0, 0, 0, 0, 0, 0, 0, 0, 0, 0, 1, 1, 0, 0, -1, 0, 0, 0, 0, 0, 0, 0, 0, 0, 0, -1, 0, 0, 0, 0, 0, 0, 0, 0, 0, 0, 0, 0, 0, 0, 0, -1, 0, 0, 0, 0, 0, 0, 0, 0, 0, -1, 0, 0, 0], "steps": 62, "is_goal": true}