{"map_file_path": "grid_maps/Wiconisco/occ_grid_small.txt", "start_pos": [32, 57], "goal_pos": [11, 95], "robot_rows": [32, 32, 32, 32, 32, 32, 32, 32, 32, 32, 32, 32, 32, 32, 32, 32, 32, 32, 32, 32, 32, 32, 31, 29, 27, 25, 22, 19, 17, 14, 12, 11, 11], "robot_cols": [57, 57, 57, 57, 58, 59, 61, 63, 66, 69, 72, 75, 78, 81, 84, 87, 90, 92, 94, 95, 95, 95, 95, 95, 95, 95, 95, 95, 95, 95, 95, 95, 95], "robot_speeds": [0, 0, 0, 0, 1, 1, 2, 2, 3, 3, 3, 3, 3, 3, 3, 3, 3, 2, 2, 1, 0, 0, 1, 2, 2, 2, 3, 3, 2, 3, 2, 1, 0], "robot_directions": [0, 0, 3, 2, 2, 2, 2, 2, 2, 2, 2, 2, 2, 2, 2, 2, 2, 2, 2, 2, 2, 1, 1, 1, 1, 1, 1, 1, 1, 1, 1, 1, 1], "action_accs": [-1, 0, 0, 1, 0, 1, 0, 1, 0, 0, 0, 0, 0, 0, 0, 0, -1, 0, -1, -1, 0, 1, 1, 0, 0, 1, 0, -1, 1, -1, -1, -1], "action_rots": [0, -1, -1, 0, 0, 0, 0, 0, 0, 0, 0, 0, 0, 0, 0, 0, 0, 0, 0, 0, -1, 0, 0, 0, 0, 0, 0, 0, 0, 0, 0, 0], "steps": 32, "is_goal": true}