{"map_file_path": "grid_maps/Wiconisco/occ_grid_small.txt", "start_pos": [3, 66], "goal_pos": [49, 1], "robot_rows": [3, 3, 3, 3, 3, 3, 3, 3, 3, 3, 3, 3, 3, 3, 4, 6, 9, 12, 15, 18, 21, 24, 27, 30, 33, 36, 39, 42, 45, 47, 48, 48, 48, 48, 47, 46, 46, 46, 46, 46, 46, 46, 46, 46, 46, 46, 46, 46, 46, 46, 46, 46, 46, 46, 46, 46, 46, 46, 46, 47, 48, 49, 50, 50, 50, 50, 49, 49], "robot_cols": [66, 66, 65, 63, 61, 58, 56, 53, 50, 48, 46, 45, 45, 45, 45, 45, 45, 45, 45, 45, 45, 45, 45, 45, 45, 45, 45, 45, 45, 45, 45, 45, 45, 45, 45, 45, 45, 45, 44, 43, 41, 38, 35, 33, 30, 27, 24, 21, 18, 15, 12, 10, 7, 4, 2, 2, 1, 1, 1, 1, 1, 1, 1, 1, 1, 1, 1, 1], "robot_speeds": [0, 0, 1, 2, 2, 3, 2, 3, 3, 2, 2, 1, 0, 0, 1, 2, 3, 3, 3, 3, 3, 3, 3, 3, 3, 3, 3, 3, 3, 2, 1, 0, 0, 0, 1, 1, 0, 0, 1, 1, 2, 3, 3, 2, 3, 3, 3, 3, 3, 3, 3, 2, 3, 3, 2, 0, 1, 0, 0, 1, 1, 1, 1, 0, 0, 0, 1, 0], "robot_directions": [0, 0, 0, 0, 0, 0, 0, 0, 0, 0, 0, 0, 0, 3, 3, 3, 3, 3, 3, 3, 3, 3, 3, 3, 3, 3, 3, 3, 3, 3, 3, 3, 0, 1, 1, 1, 1, 0, 0, 0, 0, 0, 0, 0, 0, 0, 0, 0, 0, 0, 0, 0, 0, 0, 0, 0, 0, 0, 3, 3, 3, 3, 3, 3, 0, 1, 1, 1], "action_accs": [-1, 1, 1, 0, 1, -1, 1, 0, -1, 0, -1, -1, 0, 1, 1, 1, 0, 0, 0, 0, 0, 0, 0, 0, 0, 0, 0, 0, -1, -1, -1, 0, 0, 1, 0, -1, 0, 1, 0, 1, 1, 0, -1, 1, 0, 0, 0, 0, 0, 0, -1, 1, 0, -1, 0, 1, -1, 0, 1, 0, 0, 0, -1, 0, 0, 1, -1], "action_rots": [0, 0, 0, 0, 0, 0, 0, 0, 0, 0, 0, 0, -1, 0, 0, 0, 0, 0, 0, 0, 0, 0, 0, 0, 0, 0, 0, 0, 0, 0, 0, 1, 1, 0, 0, 0, -1, 0, 0, 0, 0, 0, 0, 0, 0, 0, 0, 0, 0, 0, 0, 0, 0, 0, 0, 0, 0, -1, 0, 0, 0, 0, 0, 1, 1, 0, 0], "steps": 67, "is_goal": true}