{"map_file_path": "grid_maps/Wiconisco/occ_grid_small.txt", "start_pos": [8, 49], "goal_pos": [52, 62], "robot_rows": [8, 8, 8, 8, 8, 8, 9, 11, 14, 17, 20, 23, 26, 29, 32, 35, 38, 41, 44, 47, 50, 52, 53, 53, 53, 53, 53, 53, 53, 53, 53, 53, 53, 53, 52, 52], "robot_cols": [49, 49, 48, 47, 47, 47, 47, 47, 47, 47, 47, 47, 47, 47, 47, 47, 47, 47, 47, 47, 47, 47, 47, 47, 47, 48, 50, 53, 56, 59, 61, 62, 62, 62, 62, 62], "robot_speeds": [0, 0, 1, 1, 0, 0, 1, 2, 3, 3, 3, 3, 3, 3, 3, 3, 3, 3, 3, 3, 3, 2, 1, 0, 0, 1, 2, 3, 3, 3, 2, 1, 0, 0, 1, 0], "robot_directions": [0, 0, 0, 0, 0, 3, 3, 3, 3, 3, 3, 3, 3, 3, 3, 3, 3, 3, 3, 3, 3, 3, 3, 3, 2, 2, 2, 2, 2, 2, 2, 2, 2, 1, 1, 1], "action_accs": [-1, 1, 0, -1, 0, 1, 1, 1, 0, 0, 0, 0, 0, 0, 0, 1, 0, 0, 0, 0, -1, -1, 0, 0, 1, 1, 1, 0, 0, -1, -1, -1, 0, 1, -1], "action_rots": [0, 0, 0, 0, -1, 0, 0, 0, 0, 0, 0, 0, 0, 0, 0, 0, 0, 0, 0, 0, 0, 0, 0, -1, 0, 0, 0, 0, 0, 0, 0, 0, -1, 0, 0], "steps": 35, "is_goal": true}