{"map_file_path": "grid_maps/Wiconisco/occ_grid_small.txt", "start_pos": [47, 92], "goal_pos": [22, 56], "robot_rows": [47, 47, 47, 46, 45, 43, 40, 37, 34, 31, 28, 25, 23, 22, 22, 22, 22, 22, 22, 22, 22, 22, 22, 22, 22, 22, 22, 22, 22, 22, 22, 22, 22, 22, 22], "robot_cols": [92, 92, 92, 92, 92, 92, 92, 92, 92, 92, 92, 92, 92, 92, 92, 92, 92, 92, 92, 91, 89, 86, 83, 80, 77, 74, 72, 69, 66, 63, 60, 58, 57, 56, 56], "robot_speeds": [0, 0, 0, 1, 1, 2, 3, 3, 3, 3, 3, 3, 2, 1, 0, 0, 0, 0, 0, 1, 2, 3, 3, 3, 3, 3, 2, 3, 3, 3, 3, 2, 1, 1, 0], "robot_directions": [0, 0, 1, 1, 1, 1, 1, 1, 1, 1, 1, 1, 1, 1, 1, 1, 1, 0, 0, 0, 0, 0, 0, 0, 0, 0, 0, 0, 0, 0, 0, 0, 0, 0, 0], "action_accs": [-1, 0, 1, 0, 1, 1, 0, 0, 0, 0, 0, -1, -1, -1, 0, 0, 0, 0, 1, 1, 1, 0, 0, 0, 0, -1, 1, 0, 0, 0, -1, -1, 0, -1], "action_rots": [0, 1, 0, 0, 0, 0, 0, 0, 0, 0, 0, 0, 0, 0, 0, 0, -1, 0, 0, 0, 0, 0, 0, 0, 0, 0, 0, 0, 0, 0, 0, 0, 0, 0], "steps": 34, "is_goal": true}