{"map_file_path": "grid_maps/Wiconisco/occ_grid_small.txt", "start_pos": [66, 8], "goal_pos": [3, 59], "robot_rows": [66, 66, 66, 66, 66, 66, 66, 66, 66, 66, 66, 66, 66, 66, 66, 66, 66, 66, 66, 66, 66, 65, 63, 61, 58, 55, 52, 49, 46, 43, 40, 37, 34, 31, 28, 25, 22, 20, 19, 19, 18, 18, 18, 18, 18, 18, 18, 18, 18, 18, 18, 18, 18, 18, 18, 17, 15, 12, 9, 6, 4, 3, 3], "robot_cols": [8, 8, 8, 8, 9, 11, 14, 17, 20, 23, 26, 29, 31, 34, 36, 38, 40, 41, 41, 41, 41, 41, 41, 41, 41, 41, 41, 41, 41, 41, 41, 41, 41, 41, 41, 41, 41, 41, 41, 41, 41, 41, 41, 42, 44, 46, 49, 52, 55, 57, 58, 58, 59, 59, 59, 59, 59, 59, 59, 59, 59, 59, 59], "robot_speeds": [0, 0, 0, 0, 1, 2, 3, 3, 3, 3, 3, 3, 2, 3, 2, 2, 2, 1, 0, 0, 0, 1, 2, 2, 3, 3, 3, 3, 3, 3, 3, 3, 3, 3, 3, 3, 3, 2, 1, 0, 1, 0, 0, 1, 2, 2, 3, 3, 3, 2, 1, 0, 1, 0, 0, 1, 2, 3, 3, 3, 2, 1, 0], "robot_directions": [0, 0, 3, 2, 2, 2, 2, 2, 2, 2, 2, 2, 2, 2, 2, 2, 2, 2, 2, 2, 1, 1, 1, 1, 1, 1, 1, 1, 1, 1, 1, 1, 1, 1, 1, 1, 1, 1, 1, 1, 1, 1, 2, 2, 2, 2, 2, 2, 2, 2, 2, 2, 2, 2, 1, 1, 1, 1, 1, 1, 1, 1, 1], "action_accs": [-1, 0, 0, 1, 1, 1, 0, 0, 0, 0, 0, -1, 1, -1, 0, 0, -1, -1, 0, 0, 1, 1, 0, 1, 0, 0, 0, 1, 0, 0, 0, 0, 0, 0, 0, 0, -1, -1, -1, 1, -1, 0, 1, 1, 0, 1, 0, 0, -1, -1, -1, 1, -1, 0, 1, 1, 1, 0, 0, -1, -1, -1], "action_rots": [0, -1, -1, 0, 0, 0, 0, 0, 0, 0, 0, 0, 0, 0, 0, 0, 0, 0, 0, -1, 0, 0, 0, 0, 0, 0, 0, 0, 0, 0, 0, 0, 0, 0, 0, 0, 0, 0, 0, 0, 0, 1, 0, 0, 0, 0, 0, 0, 0, 0, 0, 0, 0, -1, 0, 0, 0, 0, 0, 0, 0, 0], "steps": 62, "is_goal": true}