{"map_file_path": "grid_maps/Wiconisco/occ_grid_small.txt", "start_pos": [33, 29], "goal_pos": [46, 90], "robot_rows": [33, 33, 33, 33, 33, 33, 33, 33, 33, 33, 33, 33, 33, 33, 33, 33, 33, 33, 33, 33, 33, 33, 33, 33, 33, 33, 33, 33, 33, 34, 36, 38, 41, 43, 45, 46, 46], "robot_cols": [29, 29, 29, 29, 30, 32, 35, 38, 41, 43, 46, 49, 52, 55, 57, 60, 63, 66, 69, 72, 75, 78, 81, 84, 87, 89, 90, 90, 90, 90, 90, 90, 90, 90, 90, 90, 90], "robot_speeds": [0, 0, 0, 0, 1, 2, 3, 3, 3, 2, 3, 3, 3, 3, 2, 3, 3, 3, 3, 3, 3, 3, 3, 3, 3, 2, 1, 0, 0, 1, 2, 2, 3, 2, 2, 1, 0], "robot_directions": [0, 0, 3, 2, 2, 2, 2, 2, 2, 2, 2, 2, 2, 2, 2, 2, 2, 2, 2, 2, 2, 2, 2, 2, 2, 2, 2, 2, 3, 3, 3, 3, 3, 3, 3, 3, 3], "action_accs": [-1, 0, 0, 1, 1, 1, 0, 0, -1, 1, 0, 0, 0, -1, 1, 0, 0, 0, 0, 0, 0, 0, 0, 0, -1, -1, -1, 0, 1, 1, 0, 1, -1, 0, -1, -1], "action_rots": [0, -1, -1, 0, 0, 0, 0, 0, 0, 0, 0, 0, 0, 0, 0, 0, 0, 0, 0, 0, 0, 0, 0, 0, 0, 0, 0, 1, 0, 0, 0, 0, 0, 0, 0, 0], "steps": 36, "is_goal": true}