{"map_file_path": "grid_maps/Wiconisco/occ_grid_small.txt", "start_pos": [34, 14], "goal_pos": [46, 76], "robot_rows": [34, 34, 34, 34, 34, 34, 34, 34, 34, 34, 34, 34, 34, 34, 34, 34, 34, 34, 34, 34, 34, 34, 34, 34, 34, 35, 36, 38, 41, 44, 47, 50, 52, 53, 53, 53, 53, 53, 53, 53, 53, 53, 53, 53, 53, 53, 53, 53, 53, 53, 52, 51, 49, 47, 46, 45, 44, 44, 44, 44, 45, 46, 46], "robot_cols": [14, 14, 14, 14, 14, 15, 17, 20, 22, 25, 28, 31, 34, 36, 39, 42, 45, 47, 48, 48, 48, 48, 47, 47, 47, 47, 47, 47, 47, 47, 47, 47, 47, 47, 47, 47, 48, 50, 53, 56, 59, 62, 65, 68, 71, 73, 75, 76, 76, 76, 76, 76, 76, 76, 76, 76, 76, 76, 76, 76, 76, 76, 76], "robot_speeds": [0, 0, 0, 0, 0, 1, 2, 3, 2, 3, 3, 3, 3, 2, 3, 3, 3, 2, 1, 0, 0, 0, 1, 0, 0, 1, 1, 2, 3, 3, 3, 3, 2, 1, 0, 0, 1, 2, 3, 3, 3, 3, 3, 3, 3, 2, 2, 1, 0, 0, 1, 1, 2, 2, 1, 1, 1, 0, 0, 0, 1, 1, 0], "robot_directions": [0, 0, 3, 2, 2, 2, 2, 2, 2, 2, 2, 2, 2, 2, 2, 2, 2, 2, 2, 2, 3, 0, 0, 0, 3, 3, 3, 3, 3, 3, 3, 3, 3, 3, 3, 2, 2, 2, 2, 2, 2, 2, 2, 2, 2, 2, 2, 2, 2, 1, 1, 1, 1, 1, 1, 1, 1, 1, 0, 3, 3, 3, 3], "action_accs": [-1, 0, 0, 0, 1, 1, 1, -1, 1, 0, 0, 1, -1, 1, 0, 0, -1, -1, -1, 0, 0, 1, -1, 0, 1, 0, 1, 1, 0, 0, 0, -1, -1, -1, 0, 1, 1, 1, 0, 0, 0, 0, 0, 0, -1, 0, -1, -1, 0, 1, 0, 1, 0, -1, 0, 0, -1, 0, 0, 1, 0, -1], "action_rots": [0, -1, -1, 0, 0, 0, 0, 0, 0, 0, 0, 0, 0, 0, 0, 0, 0, 0, 0, 1, 1, 0, 0, -1, 0, 0, 0, 0, 0, 0, 0, 0, 0, 0, -1, 0, 0, 0, 0, 0, 0, 0, 0, 0, 0, 0, 0, 0, -1, 0, 0, 0, 0, 0, 0, 0, 0, -1, -1, 0, 0, 0], "steps": 62, "is_goal": true}