{"map_file_path": "grid_maps/Wiconisco/occ_grid_small.txt", "start_pos": [42, 31], "goal_pos": [8, 47], "robot_rows": [42, 42, 42, 42, 42, 42, 42, 42, 42, 42, 42, 42, 42, 42, 42, 42, 41, 39, 36, 33, 30, 27, 24, 21, 18, 15, 12, 10, 9, 8, 8], "robot_cols": [31, 31, 31, 31, 31, 31, 32, 34, 37, 40, 43, 45, 46, 47, 47, 47, 47, 47, 47, 47, 47, 47, 47, 47, 47, 47, 47, 47, 47, 47, 47], "robot_speeds": [0, 0, 0, 0, 0, 0, 1, 2, 3, 3, 3, 2, 1, 1, 0, 0, 1, 2, 3, 3, 3, 3, 3, 3, 3, 3, 3, 2, 1, 1, 0], "robot_directions": [0, 0, 3, 3, 2, 2, 2, 2, 2, 2, 2, 2, 2, 2, 2, 1, 1, 1, 1, 1, 1, 1, 1, 1, 1, 1, 1, 1, 1, 1, 1], "action_accs": [-1, 0, 0, 0, 0, 1, 1, 1, 0, 0, -1, -1, 0, -1, 0, 1, 1, 1, 0, 0, 0, 0, 0, 0, 0, 0, -1, -1, 0, -1], "action_rots": [0, -1, 0, -1, 0, 0, 0, 0, 0, 0, 0, 0, 0, 0, -1, 0, 0, 0, 0, 0, 0, 0, 0, 0, 0, 0, 0, 0, 0, 0], "steps": 30, "is_goal": true}