{"map_file_path": "grid_maps/Wiconisco/occ_grid_small.txt", "start_pos": [53, 25], "goal_pos": [23, 88], "robot_rows": [53, 53, 53, 52, 50, 47, 44, 41, 38, 35, 32, 29, 27, 25, 24, 23, 23, 23, 23, 23, 23, 23, 23, 23, 23, 23, 23, 23, 23, 23, 23, 23, 23, 23, 23, 23, 23, 23, 23, 23, 23, 23, 23], "robot_cols": [25, 25, 25, 25, 25, 25, 25, 25, 25, 25, 25, 25, 25, 25, 25, 25, 25, 25, 26, 28, 31, 34, 37, 40, 43, 46, 49, 52, 55, 57, 60, 63, 66, 69, 72, 75, 78, 81, 84, 86, 87, 88, 88], "robot_speeds": [0, 0, 0, 1, 2, 3, 3, 3, 3, 3, 3, 3, 2, 2, 1, 1, 0, 0, 1, 2, 3, 3, 3, 3, 3, 3, 3, 3, 3, 2, 3, 3, 3, 3, 3, 3, 3, 3, 3, 2, 1, 1, 0], "robot_directions": [0, 0, 1, 1, 1, 1, 1, 1, 1, 1, 1, 1, 1, 1, 1, 1, 1, 2, 2, 2, 2, 2, 2, 2, 2, 2, 2, 2, 2, 2, 2, 2, 2, 2, 2, 2, 2, 2, 2, 2, 2, 2, 2], "action_accs": [-1, 0, 1, 1, 1, 0, 0, 0, 0, 0, 0, -1, 0, -1, 0, -1, 0, 1, 1, 1, 0, 0, 0, 0, 0, 0, 1, 0, -1, 1, 0, 0, 0, 0, 0, 0, 0, 0, -1, -1, 0, -1], "action_rots": [0, 1, 0, 0, 0, 0, 0, 0, 0, 0, 0, 0, 0, 0, 0, 0, 1, 0, 0, 0, 0, 0, 0, 0, 0, 0, 0, 0, 0, 0, 0, 0, 0, 0, 0, 0, 0, 0, 0, 0, 0, 0], "steps": 42, "is_goal": true}